cels/__init__.py
cels/default.py
cels/exceptions.py
cels/logs.py
cels/paths.py
cels/version.py
cels/cli/__init__.py
cels/cli/patch.py
cels/cli/version.py
cels/cli/describe/__init__.py
cels/cli/describe/operation.py
cels/cli/list/__init__.py
cels/cli/list/operations.py
cels/data/operations.yaml
cels/lib/__init__.py
cels/lib/json_dumps/__init__.py
cels/lib/json_dumps/dumpers.py
cels/lib/safe/__init__.py
cels/lib/safe/make_safe.py
cels/lib/safe/mutated_dict.py
cels/lib/safe/mutated_list.py
cels/lib/safe/safe_del.py
cels/lib/safe/safe_del_value.py
cels/lib/safe/safe_extend.py
cels/lib/safe/safe_get.py
cels/lib/safe/safe_set.py
cels/lib/safe/safe_traverse.py
cels/lib/show/__init__.py
cels/lib/show/show.py
cels/lib/show/show_index.py
cels/lib/show/show_type.py
cels/lib/yaml_parsing/__init__.py
cels/lib/yaml_parsing/dumpers.py
cels/lib/yaml_parsing/field_types.py
cels/lib/yaml_parsing/loaders.py
cels/models/__init__.py
cels/models/annotated_key.py
cels/models/annotation.py
cels/models/annotation_config.py
cels/models/change.py
cels/models/key_location.py
cels/models/operation.py
cels/models/patch.py
cels/models/path.py
cels/models/actions/__init__.py
cels/models/actions/action_delete.py
cels/models/actions/action_delete_value.py
cels/models/actions/action_extend.py
cels/models/actions/action_insert.py
cels/models/actions/action_keep.py
cels/models/actions/action_link.py
cels/models/actions/action_patch.py
cels/models/actions/action_rename.py
cels/models/actions/action_render.py
cels/models/actions/action_set.py
cels/models/actions/action_use.py
cels/services/__init__.py
cels/services/patch_dictionary.py
cels/services/patch_document.py
cels/services/patch_json.py
cels/services/patch_toml.py
cels/services/patch_yaml.py
cels-0.4.1.dist-info/METADATA
cels-0.4.1.dist-info/WHEEL
cels-0.4.1.dist-info/entry_points.txt
cels-0.4.1.dist-info/licenses/LICENSE
cels-0.4.1.dist-info/RECORD
