Metadata-Version: 2.4
Name: cels
Version: 0.4.1
Summary: Patch your YAML and JSON files.
Project-URL: Homepage, https://github.com/pacha/cels
Project-URL: Bug Tracker, https://github.com/pacha/cels/issues
Author-email: Andrés Sopeña Pérez <code@ehmm.org>
License-File: LICENSE
Classifier: License :: OSI Approved :: MIT License
Classifier: Operating System :: OS Independent
Classifier: Programming Language :: Python :: 3 :: Only
Classifier: Programming Language :: Python :: 3.9
Classifier: Programming Language :: Python :: 3.10
Classifier: Programming Language :: Python :: 3.11
Classifier: Programming Language :: Python :: 3.12
Requires-Python: >=3.9
Requires-Dist: click>=8.1.5
Requires-Dist: jinja2>=3.1.2
Requires-Dist: pyyaml>=6.0.1
Requires-Dist: rich>=13.5.2
Requires-Dist: tomli-w>=1.0.0
Requires-Dist: tomli>=2.0.1
Requires-Dist: typeguard>=4.0.0
Provides-Extra: code-formatting
Requires-Dist: black; extra == 'code-formatting'
Provides-Extra: dev
Requires-Dist: black; extra == 'dev'
Requires-Dist: mypy; extra == 'dev'
Requires-Dist: pytest; extra == 'dev'
Requires-Dist: types-pyyaml; extra == 'dev'
Provides-Extra: publish
Requires-Dist: build; extra == 'publish'
Provides-Extra: tests
Requires-Dist: pytest; extra == 'tests'
Provides-Extra: type-checks
Requires-Dist: mypy; extra == 'type-checks'
Requires-Dist: types-pyyaml; extra == 'type-checks'
